blacklist/__init__.py
blacklist/admin.py
blacklist/middleware.py
blacklist/models.py
blacklist/ratelimit.py
blacklist/management/commands/trim_blacklist.py
blacklist/migrations/0001_initial.py
blacklist/migrations/__init__.py
django_blacklist-0.7.0.dist-info/LICENSE
django_blacklist-0.7.0.dist-info/METADATA
django_blacklist-0.7.0.dist-info/WHEEL
django_blacklist-0.7.0.dist-info/top_level.txt
django_blacklist-0.7.0.dist-info/RECORD
