Metadata-Version: 2.1
Name: django-blacklist
Version: 0.7.0
Summary: Blacklist users and hosts in Django. Automatically blacklist rate-limited clients.
Home-page: https://github.com/vsemionov/django-blacklist
Author: Victor Semionov
Author-email: vsemionov@gmail.com
License: MIT
Keywords: django blacklist ratelimit firewall
Classifier: Development Status :: 4 - Beta
Classifier: Environment :: Web Environment
Classifier: Framework :: Django
Classifier: Intended Audience :: Developers
Classifier: License :: OSI Approved :: MIT License
Classifier: Operating System :: OS Independent
Classifier: Programming Language :: Python :: 3
Classifier: Topic :: Internet :: WWW/HTTP
Classifier: Topic :: Security
License-File: LICENSE
